meshtastic_mqtt/__init__.py
meshtastic_mqtt/admin_pb2.py
meshtastic_mqtt/apponly_pb2.py
meshtastic_mqtt/channel_pb2.py
meshtastic_mqtt/deviceonly_pb2.py
meshtastic_mqtt/environmental_measurement_pb2.py
meshtastic_mqtt/mesh_pb2.py
meshtastic_mqtt/meshtastic_mqtt.py
meshtastic_mqtt/mqtt_pb2.py
meshtastic_mqtt/portnums_pb2.py
meshtastic_mqtt/radioconfig_pb2.py
meshtastic_mqtt/remote_hardware_pb2.py
meshtastic_mqtt/storeforward_pb2.py
meshtastic_mqtt-1.0.1.dist-info/METADATA
meshtastic_mqtt-1.0.1.dist-info/WHEEL
meshtastic_mqtt-1.0.1.dist-info/entry_points.txt
meshtastic_mqtt-1.0.1.dist-info/top_level.txt
meshtastic_mqtt-1.0.1.dist-info/RECORD
