Metadata-Version: 2.1
Name: meshtastic-mqtt
Version: 1.0.1
Summary: A python script to translate Meshtastic MQTT location messages into a format that Traccar can understand.
Home-page: https://github.com/joshpirihi/meshtastic-mqtt
Author: joshpirihi
License: MIT
Platform: UNKNOWN
Classifier: License :: OSI Approved :: MIT License
Classifier: Programming Language :: Python :: 3
Classifier: Programming Language :: Python :: 3.7
Requires-Python: >=3.6
Requires-Dist: protobuf (>=3.13.0)
Requires-Dist: pypubsub (>=4.0.3)
Requires-Dist: requests
Requires-Dist: paho-mqtt
